Metadata-Version: 1.1
Name: papy
Version: 1.0.7
Summary: flow-based, parallel and distributed computational pipelines, includes a lazy, parallel, remote, multi-task map function
Home-page: http://mcieslik-mctp.github.io/papy/
Author: Marcin Cieslik
Author-email: mcieslik@med.umich.edu
License: BSD
Keywords: multiprocessing,parallel,distributed,pool,imap,workflow,pipeline,flow-based
Platform: UNKNOWN
Classifier: Development Status :: 4 - Beta
Classifier: Operating System :: OS Independent
Classifier: Intended Audience :: Developers
Classifier: Intended Audience :: Science/Research
Classifier: Topic :: Scientific/Engineering
Classifier: Programming Language :: Python :: 2.7
Classifier: License :: OSI Approved :: BSD License
